pbokit/__init__.py
pbokit/pbo.py
pbokit-0.2.0.dist-info/METADATA
pbokit-0.2.0.dist-info/WHEEL
pbokit-0.2.0.dist-info/top_level.txt
pbokit-0.2.0.dist-info/RECORD
