Metadata-Version: 2.1
Name: pbokit
Version: 0.2.0
Summary: Fully-typed Arma 3 PBO extractor library
Author: Superxpdude
Project-URL: Repository, https://github.com/Superxpdude/pbokit
Requires-Python: >=3.10
